TVRegex-0.1.1.dist-info/DESCRIPTION.rst
TVRegex-0.1.1.dist-info/METADATA
TVRegex-0.1.1.dist-info/RECORD
TVRegex-0.1.1.dist-info/WHEEL
TVRegex-0.1.1.dist-info/entry_points.txt
TVRegex-0.1.1.dist-info/metadata.json
TVRegex-0.1.1.dist-info/top_level.txt
tvregex/__init__.py
tvregex/shownames.json
tvregex/tvregex.py
