Metadata-Version: 2.0
Name: TVRegex
Version: 0.1.1
Summary: Regex-only TV show renamer. No TVDB required!
Home-page: https://github.com/ROldford/tvregex
Author: Ryan Oldford
Author-email: ryan.oldford@gmail.com
License: MIT
Platform: UNKNOWN
Classifier: Development Status :: 3 - Alpha
Classifier: Intended Audience :: End Users/Desktop
Classifier: License :: OSI Approved :: MIT License
Classifier: Programming Language :: Python :: 3
Classifier: Programming Language :: Python :: 3.3
Classifier: Programming Language :: Python :: 3.4
Classifier: Programming Language :: Python :: 3.5
Classifier: Programming Language :: Python :: 3.6
Requires-Python: >=3
